kedro_diff/__init__.py
kedro_diff/__main__.py
kedro_diff/cli.py
kedro_diff/commit_parser.py
kedro_diff/diff.py
kedro_diff/errors.py
kedro_diff/get_pipelines.py
kedro_diff/logger.py
kedro_diff/sample_data.py
kedro_diff/node_diff/__init__.py
kedro_diff/node_diff/__main__.py
kedro_diff/node_diff/node_diff.py
tests/__init__.py
tests/test_commit_parser.py
tests/test_diff.py
tests/test_load_commit_metadata.py
tests/test_main.py
tests/test_node_diff.py
tests/test_node_diff_main.py
kedro_diff-0.1.1.dist-info/LICENSE
kedro_diff-0.1.1.dist-info/METADATA
kedro_diff-0.1.1.dist-info/WHEEL
kedro_diff-0.1.1.dist-info/entry_points.txt
kedro_diff-0.1.1.dist-info/top_level.txt
kedro_diff-0.1.1.dist-info/RECORD
