Metadata-Version: 2.1
Name: kedro-diff
Version: 0.1.1
Summary: diff commits to your kedro pipeline
Home-page: https://github.com/WaylonWalker/kedro-diff
Author: Waylon Walker
License: OSI APPROVED :: MIT LICENSE
Keywords: pipelines,machine learning,data pipelines,data science,data engineering
Platform: any
Classifier: Development Status :: 4 - Beta
Classifier: Environment :: Plugins
Classifier: Framework :: Kedro
Classifier: Intended Audience :: Developers
Classifier: Operating System :: Microsoft :: Windows
Classifier: Operating System :: MacOS
Classifier: Operating System :: POSIX :: Linux
Classifier: Programming Language :: Python :: 3.6
Classifier: Programming Language :: Python :: 3.7
Classifier: Programming Language :: Python :: 3.8
Classifier: Programming Language :: Python :: 3.9
Classifier: Programming Language :: Python :: 3.10
Classifier: Typing :: Typed
Requires-Dist: click
Requires-Dist: kedro
Requires-Dist: more-itertools
Requires-Dist: rich
Provides-Extra: dev
Requires-Dist: black (==20.8b1) ; extra == 'dev'
Requires-Dist: bump2version ; extra == 'dev'
Requires-Dist: flake8 (==3.9.0) ; extra == 'dev'
Requires-Dist: interrogate ; extra == 'dev'
Requires-Dist: isort (==5.8.0) ; extra == 'dev'
Requires-Dist: mypy (==0.812) ; extra == 'dev'
Requires-Dist: pre-commit ; extra == 'dev'
Requires-Dist: pytest ; extra == 'dev'
Requires-Dist: pytest-cov ; extra == 'dev'
Requires-Dist: pytest-mock ; extra == 'dev'
Requires-Dist: setuptools ; extra == 'dev'
Requires-Dist: wheel ; extra == 'dev'
